README.md
setup.py
crypto_ecc/__init__.py
crypto_ecc/crypto_ecc.py
crypto_ecc.egg-info/PKG-INFO
crypto_ecc.egg-info/SOURCES.txt
crypto_ecc.egg-info/dependency_links.txt
crypto_ecc.egg-info/not-zip-safe
crypto_ecc.egg-info/top_level.txt