Metadata-Version: 1.0
Name: crypto-ecc
Version: 0.4
Summary: ECC hepler functions
Home-page: UNKNOWN
Author: FEEDFACE
Author-email: muutax@hotmail.com
License: MIT
Platform: UNKNOWN
